{
  "workspaceId": "1014",
  "designSystemId": "1197",
  "designSystemVersionId": "16463",
  "brandId": "15914",
  "exporterId": "134",
  "workspaceName": "EDNet",
  "designSystemName": "EDNet Design sysytem",
  "designSystemVersionName": "Init",
  "exporterName": "Custom Flutter exporter",
  "write_to": "/lib/supernova",
  "description": "Note to our fellow developers: Install Supernova integration from the VSCode marketplace and then our  Custom Flutter exporter exporter will synchronize design data and generate appropriate code from the  Init design system every time you request it through the extension interface, fully automatically."
}